{"1309352":{"name":"Ferrocarril Trasandino Los Andes - Mendoza","type":"route","route":"railway","name:de":"Transandenbahn","name:en":"Transandine Railway","end_date":"1984","wikidata":"Q1254317","abandoned":"yes","wikipedia":"es:Ferrocarril Trasandino Los Andes-Mendoza","start_date":"1910-04-05"},"1636438":{"name":"Ramal Bahía Blanca - Zapala","type":"route","route":"railway","wikidata":"Q6099062"},"1983433":{"to":"Santa Fe","ref":"F1","via":"Rosario","from":"Ramal F1","name":"FC Belgrano: Ramal F1 → Rosario → Santa Fe","type":"route","route":"railway","network":"Belgrano","wikidata":"Q5573045","wikipedia":"es:Ramal F1 del Ferrocarril Belgrano"},"2092853":{"name":"Ramal Ferroviario Destilería YPF","type":"route","route":"railway","network":"San Martín"},"6445519":{"to":"Salta","ref":"FCAS","from":"Antofagasta","name":"Ferrocarril de Antofagasta a Salta","type":"route","route":"railway","name:de":"Bahnstrecke Salta–Antofagasta","name:en":"Salta–Antofagasta railway","alt_name":"Huaytiquina","operator":"Ferronor - Trenes Argentinos","wikidata":"Q17087292","wikipedia":"es:Ferrocarril Antofagasta-Salta","start_date":"1948-02-20"},"10115931":{"name":"Chascomús Viejo","type":"route","route":"railway"},"13679282":{"ref":"CC-2","name":"Ramal CC2 del Ferrocarril Belgrano","type":"route","route":"railway","network":"Belgrano","end_date":"2015","operator":"Trenes Argentinos Cargas","wikidata":"Q85876802","wikipedia":"es:Ramal CC2 del Ferrocarril Belgrano","description":"Sin operaciones. Vías intrusadas."},"13924538":{"name":"Ramal Retiro - Empalme Norte - Kilómetro 5","type":"route","route":"railway","wikidata":"Q19677212"},"13968401":{"ref":"GM-46","name":"Ramal GM-46","type":"route","route":"railway","network":"Mitre","wikidata":"Q97168558","wikipedia":"es:Ramal ferroviario Peyrano-Wheelwright-Rastreador Fournier"},"13968402":{"ref":"GM-31","name":"Ramal GM-31","type":"route","route":"railway","network":"Mitre","wikidata":"Q20890277","wikipedia":"es:Ramal ferroviario Rosario-Casilda-Río Tercero-Córdoba"},"13968403":{"ref":"GM-15","name":"Ramal GM-15","type":"route","route":"railway","network":"Mitre","wikidata":"Q19369034","wikipedia":"es:Ramal ferroviario Pergamino-Cañada de Gómez"},"13968449":{"name":"Ramal GM-19 Pérez-Soldini-Peyrano","type":"route","route":"railway"},"13968497":{"name":"Ramal GM-13 Villa Constitución - Río Cuarto","type":"route","route":"railway","network":"Mitre","wikidata":"Q19366421","wikipedia":"es:Ramal ferroviario Villa Constitución-Río Cuarto"},"13968537":{"ref":"GM-44","name":"Ramal GM-44","type":"route","route":"railway","network":"Mitre"},"13968560":{"ref":"GM-9","name":"Ramal GM-9 Rosario-Casilda-Río Tercero-Córdoba","type":"route","route":"railway","wikidata":"Q20890277","wikipedia":"es:Ramal ferroviario Rosario-Casilda-Río Tercero-Córdoba"},"13968932":{"name":"Ramal GM-39","type":"route","route":"railway"},"13968961":{"name":"Ramal GM-24","type":"route","route":"railway"},"13968981":{"name":"Ramal GM-27 Pilar-Villa del Rosario","type":"route","route":"railway"},"13968982":{"name":"Ramal GM-45","type":"route","route":"railway"},"13969010":{"name":"Ramal GM-37","type":"route","route":"railway"},"13969053":{"name":"Ramal GM-65","type":"route","route":"railway"},"13969086":{"name":"Ramal GM-63","type":"route","route":"railway"},"13969087":{"ref":"GM-14","name":"Ramal GM-14 Cañada de Gómez-Zenón Pereyra","type":"route","route":"railway","network":"Mitre"},"13969698":{"ref":"GM-33","name":"Ramal GM-33","type":"route","route":"railway"},"13969699":{"name":"Ramal GM-10 Casilda-Firmat-San Urbano","type":"route","route":"railway"},"13969765":{"name":"Ramal GM-41","type":"route","route":"railway"},"13969783":{"name":"Ramal GM-64","type":"route","route":"railway"},"13969820":{"name":"Ramal GM-21 Santa Fe-Bernardo de Irigoyen","type":"route","route":"railway"},"13969821":{"name":"Ramal GM-22 Gálvez-San Francisco-La Rubia","type":"route","route":"railway"},"13970025":{"ref":"GM-7","name":"Ramal GM-7","type":"route","route":"railway","network":"Mitre"},"13970104":{"name":"Ramal GM-11 Córdoba-Malagueño","type":"route","route":"railway"},"13970124":{"name":"Ramal GM-35","type":"route","route":"railway"},"13970130":{"name":"Ramal GM-36","type":"route","route":"railway"},"15895919":{"to":"Puerto de Rosario","ref":"G-07","from":"Rosario F","name":"Ramal G-07","type":"route","route":"railway","network":"Belgrano","operator":"Trenes Argentinos"},"16137278":{"name":"FC Sarmiento - Relief Line","type":"route","route":"railway"},"16137279":{"from":"Once","name":"Túnel de Cargas","type":"route","route":"railway","name:de":"Cargas-Bahn"}}