{"71799":{"to":"Bf. Altona","ref":"X86","from":"Teufelsbrück (Fähre)","name":"XpressBus X86: Teufelsbrück (Fähre) => Bf. Altona","type":"route","route":"bus","colour":"#1a962b","network":"Hamburger Verkehrsverbund","operator":"Hamburger Hochbahn AG","network:short":"HVV","operator:short":"HHA","network:wikidata":"Q896916","network:wikipedia":"de:Hamburger Verkehrsverbund","operator:wikidata":"Q6442","operator:wikipedia":"de:Hamburger Hochbahn","public_transport:version":"2"},"3368020":{"to":"Hoorn, Station","ref":"136","via":"Oostwoud; Hauwert; Nibbixwoud","from":"Midwoud, Oostwouder Dorpsstraat","name":"Bus 136: Midwoud Oostwouder Dorpsstraat => Hoorn Station","type":"route","route":"bus","colour":"#0000ff","network":"Noord-Holland Noord","operator":"Connexxion","network:wikidata":"Q2271893","network:wikipedia":"nl:Concessie Noord-Holland Noord","public_transport:version":"2"},"3910539":{"to":"Baindt, Marsweiler","fee":"yes","ref":"1","via":"Ravensburg, Weingarten","from":"Schmalegg, Ortsmitte","name":"Linie 1: Schmalegg -> Ravensburg, Weingarten -> Baindt, Marsweiler","type":"route","route":"bus","colour":"#ec193b","network":"Bodensee-Oberschwaben Verkehrsverbund","operator":"Regionalverkehr Alb-Bodensee GmbH (RAB)","network:short":"bodo","operator:short":"RAB","network:wikidata":"Q889680","network:wikipedia":"de:Bodensee-Oberschwaben Verkehrsverbund","public_transport:version":"2"},"5231414":{"to":"Punta Gorda","ref":"1","name":"Ruta 1 Cienfuegos ida","type":"route","route":"bus","network":"Ruteros Cienfuegos","operator":"Omnibus Ruteros","public_transport:version":"2"},"7500708":{"to":"Bishops Bridge","ref":"16","from":"Brent Park Tesco","name":"London Buses route 16 → Paddington","note":"Intricate relation - do not auto-sort.","type":"route","route":"bus","network":"London Buses","operator":"Metroline","network:wikidata":"Q1192411","network:wikipedia":"en:London Buses","public_transport:version":"2"},"8274763":{"to":"Vocacional","ref":"10","from":"Villa Toa","name":"Ruta 10: Villa Toa => Vocacional","type":"route","route":"bus","colour":"#CD853F","public_transport:version":"2"},"8274764":{"to":"Villa Toa","ref":"10","from":"Vocacional","name":"Ruta 10: Vocacional => Villa Toa","type":"route","route":"bus","colour":"#CD853F","operator":"10","public_transport:version":"2"},"8534097":{"ref":"30","name":"Ruta 30. Dist. Abel Santamaria->Parque Abel Santamaria","type":"route","route":"bus"},"9186301":{"to":"Amistad","ref":"437","from":"Vedado","name":"Local Guines","type":"route","route":"bus","operator":"TransMayabeque","public_transport:version":"2"},"10250217":{"to":"Cuba Si","ref":"207","from":"Capitan Urbino","name":"Holguin 207 Capitan Urbino - Cuba Si","type":"route","route":"bus","public_transport:version":"2"},"10250220":{"to":"Capdevila","ref":"A11","from":"San Rafael","name":"Holguín A11 San Rafael - Capdevila -","type":"route","route":"bus","public_transport:version":"2"},"10250221":{"to":"Ciudad Jardín","ref":"A9","from":"Piedra Blanca","name":"Holguín A9 Piedra Blanca - Ciudad Jardín","type":"route","route":"bus","public_transport:version":"2"},"10250222":{"to":"Capdevila","ref":"A4","from":"Hnos Aguilera","name":"Holguín A4 Hermanos Aguilera - Capdevila -","type":"route","route":"bus","public_transport:version":"2"},"10250223":{"to":"Hnos Aguilera","ref":"A4","from":"Capdevila","name":"Holguín A4 Capdevila - Hermanos Aguilera","type":"route","route":"bus","public_transport:version":"2"},"10250224":{"to":"Salida de San Andrés","ref":"208","from":"Valle Mayabe","name":"Holguín 208 - Valle de Mayabe - Salida San Andrés","type":"route","route":"bus","public_transport:version":"2"},"10250225":{"to":"Valle de Mayabe","ref":"208","from":"Salida San Andrés","name":"Holguín 208 - Salida San Andrés - Valle de Mayabe","type":"route","route":"bus","public_transport:version":"2"},"10250226":{"to":"Loma de la Cruz","ref":"200","from":"Mayabe","name":"Holguín 200 - Mayabe Loma de la Cruz","type":"route","route":"bus","public_transport:version":"2"},"10250227":{"to":"Mayabe","ref":"200","from":"Loma de La Cruz","name":"Holguín 200 Loma de la Cruz - Mayabe","type":"route","route":"bus","public_transport:version":"2"},"10250228":{"to":"Capdevila","ref":"A10","from":"El Coco","name":"Holguín A10 El Coco Capdevila","type":"route","route":"bus","public_transport:version":"2"},"10250229":{"to":"El Coco","ref":"A10","from":"Capdevila","name":"Holguín A10 Capsevila - El Coco","type":"route","route":"bus","public_transport:version":"2"},"10250230":{"to":"Capdevila","ref":"209","from":"Aeropuerto","name":"Holguín 209 Aeropuerto - Capdevila","type":"route","route":"bus","public_transport:version":"2"},"10250231":{"to":"Aeropuerto Frank País","ref":"209","from":"Capdevila","name":"Holguín 209 Capdevila Aeropuerto","type":"route","route":"bus","public_transport:version":"2"},"10250233":{"to":"San Rafael","ref":"A11","from":"Capdevila","name":"Holguín A11 Capdevila - San Rafael","type":"route","route":"bus","public_transport:version":"2"},"10250264":{"to":"Capitan Urbino","ref":"207","from":"Cuba Si","name":"Holguin 207 - Cuba Si - Capitan Urbino","type":"route","route":"bus","public_transport:version":"2"},"11333193":{"to":"Las Novillas","ref":"34","from":"Parque Céspedes","name":"Parque Céspedes - Novillas","type":"route","route":"bus","public_transport:version":"2"},"11333287":{"to":"Combinado Lácteo","ref":"2","from":"Campestre","name":"Campestre-Combinado Lácteo","type":"route","route":"bus","public_transport:version":"2"},"11333288":{"to":"Campestre","ref":"1","from":"La Pedrera","name":"Ruta 1 La Pederera-Campestre","type":"route","route":"bus","public_transport:version":"2"},"11333289":{"to":"La Pedrera","ref":"1","from":"Campestre","name":"Ruta 1 Campestre-La Pedrera","type":"route","route":"bus","public_transport:version":"2"},"11987026":{"ref":"9","name":"Ruta 9 Matanzas (regreso)","type":"route","route":"bus","public_transport:version":"2"},"11987027":{"ref":"9","name":"Ruta 9 Matanzas (ida)","type":"route","route":"bus","public_transport:version":"2"},"11987028":{"ref":"1","name":"Ruta 1 Matanzas (regreso)","type":"route","route":"bus","public_transport:version":"2"},"11987029":{"ref":"1","name":"Ruta 1 Matanzas (ida)","type":"route","route":"bus","public_transport:version":"2"},"11987030":{"ref":"19","name":"Ruta 19 Matanzas (regreso)","type":"route","route":"bus","public_transport:version":"2"},"11987031":{"ref":"19","name":"Ruta 19 Matanzas (ida)","type":"route","route":"bus","public_transport:version":"2"},"11987032":{"to":"EIDE","ref":"25","from":"Canimar","name":"Ruta 25 Matanzas regreso)","type":"route","route":"bus","public_transport:version":"2"},"11987061":{"ref":"20","name":"Ruta 20 Matanzas (regreso)","type":"route","route":"bus","operator":"Ómnibus Yumurí","public_transport:version":"2"},"11987062":{"ref":"20","name":"Ruta 20 Matanzas (ida)","type":"route","route":"bus","operator":"Ómnibus Yumurí","public_transport:version":"2"},"11987063":{"ref":"24","name":"Ruta 24 Matanzas (regreso)","type":"route","route":"bus","operator":"Ómnibus Yumurí","public_transport:version":"2"},"11987064":{"ref":"24","name":"Ruta 24 Matanzas (ida)","type":"route","route":"bus","operator":"Ómnibus Yumurí","public_transport:version":"2"},"11989792":{"to":"Abel Santamaría","ref":"P1","from":"Combinado Textil","name":"Ruta P1. Textilera->Micro 3 A. Santamaria","type":"route","route":"bus","public_transport:version":"2"},"11989793":{"to":"Combinado Textil","ref":"P1","from":"Abel Santamaría","name":"Ruta P1. Micro 3 -> A. SantamariaTextilera","type":"route","route":"bus","public_transport:version":"2"},"12096088":{"to":"Caunao","ref":"207","from":"Villuendas","name":"Ruta 207 Cienfuegos ida","type":"route","route":"bus","public_transport:version":"2"},"12096089":{"to":"Guanábana","ref":"208","from":"Peñas Altas","name":"Ruta 208 Matanzas Guanábana","type":"route","route":"bus","public_transport:version":"2"},"12096092":{"ref":"21","name":"Ruta 21 Matanzas (regreso)","type":"route","route":"bus","operator":"Ómnibus Yumurí","public_transport:version":"2"},"12096093":{"ref":"21","name":"Ruta 21 Matanzas (ida)","type":"route","route":"bus","operator":"Ómnibus Yumurí","public_transport:version":"2"},"12564837":{"to":"Quivicán","ref":"600","via":"La Salud","from":"Santiago de las Vegas","name":"Ruta Santiago - La salud - Quivicán","type":"route","route":"bus","interval":"60","operator":"EPT Mayabeque","description":"interurbana","public_transport:version":"2"},"12863422":{"ref":"224","name":"Ruta Bauta - San Pedro","type":"route","route":"bus","operator":"ARTRA","public_transport:version":"2"},"12863424":{"ref":"434","name":"Ruta Alquízar Dagame","type":"route","route":"bus","operator":"ARTRA","public_transport:version":"2"},"12863425":{"ref":"445","name":"Ruta San Critobal - Niceto Perez","type":"route","route":"bus","operator":"ARTRA","public_transport:version":"2"},"12863426":{"ref":"207","name":"Ruta Bahía Honda Harlem","type":"route","route":"bus","operator":"ARTRA","public_transport:version":"2"},"12863427":{"ref":"410","name":"Ruta Bahía Honda San Pedro","type":"route","route":"bus","operator":"ARTRA","public_transport:version":"2"},"12863428":{"ref":"401","name":"Ruta Bahía Honda Orozco","type":"route","route":"bus","operator":"ARTRA","public_transport:version":"2"},"12863429":{"ref":"402","name":"Ruta Bahía Honda La Mulata","type":"route","route":"bus","operator":"ARTRA","public_transport:version":"2"},"12863430":{"ref":"435","name":"Ruta Alquízar - Guanímar","type":"route","route":"bus","operator":"ARTRA","public_transport:version":"2"},"12863431":{"ref":"245","name":"Ruta Gúira - La Salud","type":"route","route":"bus","operator":"ARTRA","public_transport:version":"2"},"12863432":{"ref":"430","name":"Ruta Güira - Cajío","type":"route","route":"bus","operator":"ARTRA","public_transport:version":"2"},"12863433":{"ref":"448","name":"Ruta San Critobal - Morán","type":"route","route":"bus","operator":"ARTRA","public_transport:version":"2"},"12863434":{"ref":"271","name":"Ruta San Critobal - Martí","type":"route","route":"bus","operator":"ARTRA","public_transport:version":"2"},"12863435":{"ref":"270","name":"Ruta San Critobal Lopez Peña","type":"route","route":"bus","operator":"ARTRA","public_transport:version":"2"},"12863436":{"ref":"422","name":"Ruta caimito - salado - Menelao Mora","type":"route","route":"bus","operator":"ARTRA","public_transport:version":"2"},"12863437":{"ref":"222","via":"Ceiba","name":"Ruta Caimito - Artemisa","type":"route","route":"bus","operator":"ARTRA","public_transport:version":"2"},"12863439":{"ref":"229","name":"Ruta Bauta - San Antonio","type":"route","route":"bus","operator":"ARTRA","public_transport:version":"2"},"12863440":{"ref":"231","name":"Ruta Bauta - Baracoa","type":"route","route":"bus","network":"interurbana","operator":"ARTRA","public_transport:version":"2"},"12863441":{"ref":"266","name":"Ruta Candelaria Las Terazas","type":"route","route":"bus","public_transport:version":"2"},"12863442":{"ref":"441","name":"Ruta Candelaria Soroa","type":"route","route":"bus","operator":"ARTRA","public_transport:version":"2"},"12863443":{"ref":"267","name":"Ruta Candelaria - San Cristobal","type":"route","route":"bus","operator":"ARTRA","public_transport:version":"2"},"12863444":{"ref":"418","name":"Guanajay La Sierra Rancho","type":"route","route":"bus","operator":"ARTRA","public_transport:version":"2"},"12863445":{"ref":"279","name":"Ruta Guanajay - San Antonio","type":"route","route":"bus","public_transport:version":"2"},"12863450":{"ref":"457","name":"Ruta Artemisa Pluma","type":"route","route":"bus","operator":"ARTRA","public_transport:version":"2"},"12863451":{"ref":"454","name":"Ruta 454 Artemisa Corojal","type":"route","route":"bus","operator":"ARTRA","public_transport:version":"2"},"12863452":{"ref":"210","name":"Ruta 210. Mariel-Baracoa","type":"route","route":"bus","operator":"ARTRA","public_transport:version":"2"},"12863453":{"to":"San Antonio de los Baños","ref":"252","via":"Ceiba","from":"Artemisa","name":"Ruta 252 Artemisa - San Antonio","type":"route","route":"bus","operator":"ARTRA","public_transport:version":"2"},"12863454":{"to":"Silvio Caro","ref":"212","via":"Cabañas","from":"Mariel","name":"Ruta 212 Mariel Silvio Caro","type":"route","route":"bus","public_transport:version":"2"},"12863455":{"to":"Mariel","ref":"216","from":"Guanajay","name":"Ruta 216 Guanajay - Mariel","type":"route","route":"bus","network":"interurbana","operator":"ARTRA","public_transport:version":"2"},"12863456":{"ref":"106","name":"Ruta Local Mariel","type":"route","route":"bus","network":"urban","operator":"ARTRA","public_transport:version":"2"},"13042086":{"ref":"413","name":"Ruta Bahía Honda - Morrillo","type":"route","route":"bus","operator":"ARTRA","public_transport:version":"2"},"13042087":{"ref":"403","name":"Ruta Omnibus Bahía Honda Carenero","type":"route","route":"bus","operator":"ARTRA","public_transport:version":"2"},"13363099":{"ref":"200","name":"Ruta 200 Cienfuegos","type":"route","route":"bus","public_transport:version":"2"},"13363100":{"ref":"6","name":"Ruta 6 Cienfuegos","type":"route","route":"bus","public_transport:version":"2"},"13363101":{"ref":"3","name":"Ruta 3 Cienfuegos retorno","type":"route","route":"bus","public_transport:version":"2"},"13436870":{"ref":"5","name":"Ruta 5 Las Tunas","type":"route","route":"bus","public_transport:version":"2"},"13436871":{"ref":"5","name":"Ruta 5 Las Tunas (regreso)","type":"route","route":"bus","public_transport:version":"2"},"13436976":{"ref":"2","name":"Ruta 2 Las Tunas","type":"route","route":"bus","public_transport:version":"2"},"13436977":{"ref":"1","name":"Ruta 1 Las Tunas","type":"route","route":"bus","public_transport:version":"2"},"13436978":{"ref":"1","name":"Ruta 1 Las Tunas (regreso)","type":"route","route":"bus","public_transport:version":"2"},"13436979":{"ref":"4","name":"Ruta 4 Las Tunas","type":"route","route":"bus","public_transport:version":"2"},"13436980":{"ref":"4","name":"Ruta 4 Las Tunas (regreso)","type":"route","route":"bus","public_transport:version":"2"},"13447872":{"to":"Camppestre","ref":"2","from":"Combinado Lácteo","name":"Ruta 2 Bayamo Combinado Lácteo - Campestre","type":"route","route":"bus","public_transport:version":"2"},"14241488":{"to":"Garrido","ref":"28","from":"Porvenir","name":"Ruta 28 Porvenir Garrido","type":"route","route":"bus","network":"Camaguey","public_transport:version":"2"},"14287630":{"ref":"603","name":"Ruta San Jose Quivican","type":"route","route":"bus","operator":"TransMayabeque","public_transport:version":"2"},"14287632":{"ref":"603","name":"Ruta Quivican San Jose","type":"route","route":"bus","operator":"TransMayabeque","public_transport:version":"2"},"14287633":{"ref":"232","name":"Ruta San Antonio Tumbadero","type":"route","route":"bus","operator":"ARTRA","public_transport:version":"2"},"14287634":{"ref":"429","name":"Ruta Güira - Junco","type":"route","route":"bus","operator":"ARTRA","public_transport:version":"2"},"14287635":{"ref":"240","name":"Ruta Güira - Batabanó","type":"route","route":"bus","operator":"ARTRA","public_transport:version":"2"},"14294996":{"ref":"669","name":"Ruta Guines Madruga Santa Cruz","type":"route","route":"bus","network":"interurbana","operator":"TransMayabeque","public_transport:version":"2"},"14294997":{"ref":"652","name":"Ruta urbana Batabano Surgidero","type":"route","route":"bus","network":"urban","operator":"TransMayabeque","public_transport:version":"2"},"14294998":{"ref":"688","name":"Ruta Batabanó Güines","type":"route","route":"bus","network":"interurbana","operator":"TransMayabeque","public_transport:version":"2"},"14297979":{"ref":"694","name":"Ruta San Jose Artemisa","type":"route","route":"bus","operator":"TransMayabeque","public_transport:version":"2"},"14390663":{"ref":"44","name":"Ruta 44 Moron Patria (regreso)","type":"route","route":"bus","public_transport:version":"2"},"14390664":{"ref":"44","name":"Ruta 44 Moron Patria","type":"route","route":"bus","public_transport:version":"2"},"14390665":{"ref":"41","name":"Ruta 41 Moron (Paradero Turístico) (regreso)","type":"route","route":"bus","network":"local","public_transport:version":"2"},"14390666":{"ref":"41","name":"Ruta 41 Moron (Paradero Turístico)","type":"route","route":"bus","network":"local","public_transport:version":"2"},"14390667":{"ref":"4","name":"Ómnibus ruta 4 Barbero Vivero (ida)","type":"route","route":"bus","public_transport:version":"2"},"14390669":{"ref":"cc","name":"Ruta 23 Ciego Suferry Numero 1","type":"route","route":"bus","public_transport:version":"2"},"14390670":{"ref":"cc","name":"Ruta 23 Ciego (Numero 1 Suferry)","type":"route","route":"bus","public_transport:version":"2"},"14390687":{"ref":"1","name":"Ruta 1 Ciego Barbero Grego (regreso)","type":"route","route":"bus","public_transport:version":"2"},"14390688":{"ref":"1","name":"Ruta 1 Ciego Barbero Grego (ida)","type":"route","route":"bus","public_transport:version":"2"},"14390689":{"ref":"3","name":"Ómnibus ruta 3 Barbero canaleta (ida)","type":"route","route":"bus","public_transport:version":"2"},"14413837":{"ref":"202","name":"Ruta 202 Pinar del Río","type":"route","route":"bus","public_transport:version":"2"},"14413838":{"ref":"204","name":"Ruta 204 Pinar del Río Mazon","type":"route","route":"bus","public_transport:version":"2"},"14413867":{"ref":"214","name":"Ruta 214 Pinar de Río","type":"route","route":"bus","public_transport:version":"2"},"14422047":{"ref":"207","name":"Ruta 207 Pinar del Río Aguas Claras","type":"route","route":"bus","public_transport:version":"2"},"14422048":{"ref":"203","name":"Ruta 203 Pinar del Río Entronque de Ovas","type":"route","route":"bus","public_transport:version":"2"},"14427855":{"ref":"683","name":"Ruta 683 San José Cotorro","type":"route","route":"bus","operator":"TransMayabeque","public_transport:version":"2"},"14427856":{"ref":"657","name":"Ruta 657 Jaruco Aguacate","type":"route","route":"bus","operator":"TransMayabeque","public_transport:version":"2"},"14427857":{"ref":"670","name":"Ruta 670 San Jose Jaruco Santa Cruz","type":"route","route":"bus","public_transport:version":"2"},"14427876":{"ref":"660","name":"Rura 660 San José Guines Osvaldo Sanchez","type":"route","route":"bus","operator":"TransMayabeque","public_transport:version":"2"},"14435743":{"to":"ISCAH","ref":"331","via":"Las Parcelas","from":"Ronera","name":"Ruta Local 2 San José de las Lajas","type":"route","route":"bus","operator":"TransMayabeque","public_transport:version":"2"},"14435744":{"to":"Ronera","ref":"331","via":"Las Parcelas","from":"ISCAH","name":"Ruta Local 2 San José de las Lajas","type":"route","route":"bus","operator":"TransMayabeque","public_transport:version":"2"},"14453918":{"ref":"239","name":"Ruta 239 Pinar del Río","type":"route","route":"bus","public_transport:version":"2"},"15510155":{"to":"Lenin","ref":"25","via":"Universidad","from":"Casino","name":"Ruta 25 Casino Lenin","type":"route","route":"bus","public_transport:version":"2"}}