{"575031":{"to":"Diakonissenhaus","ref":"43","from":"Seniorenzentrum Servatius","name":"Stadtbus 43: Seniorenzentrum Servatius => Diakonissenhaus","type":"route","route":"bus","colour":"#d9893d","network":"Augsburger Verkehrs- und Tarifverbund","website":"https://www.avv-augsburg.de","operator":"Augsburger Verkehrsgesellschaft mbH","network:area":"city","network:guid":"DE-BY-AVV","network:short":"AVV","network:wikidata":"Q760574","network:wikipedia":"de:Augsburger Verkehrs- und Tarifverbund","public_transport:version":"2"},"2863745":{"to":"Os. Poręba","ref":"159","from":"Mełgiewska WSEI","name":"159 : Mełgiewska WSEI - Os. Poręba Trasa Zmieniona","type":"route","route":"bus","colour":"blue","network":"Lublin","operator":"ZTM Lublin"},"2870013":{"to":"Gęsia","ref":"45","from":"Mełgiewska WSEI","name":"45 : Mełgiewska WSEI - Gęsia","type":"route","route":"bus","colour":"blue","network":"Lublin","operator":"ZTM Lublin"},"3275064":{"to":"Ostřešany, točna","ref":"10","from":"Ohrazenice, točna","name":"10: Ohrazenice, točna - Ostřešany, točna","type":"route","route":"bus","network":"MHD v Pardubicích","operator":"DPMP","public_transport:version":"2"},"6022742":{"to":"Makeni Konga","ref":"49","from":"Town (Kulima Tower)","name":"49 Town (Kulima Tower) - Makeni Konga","type":"route","route":"bus","network":"Lusaka City Council","operator":"Lusaka City Council","public_transport:version":"2"},"6022748":{"to":"Woodlands","ref":"59","from":"Town (Kulima Tower)","name":"59 Town (Kulima Tower) - Woodlands","type":"route","route":"bus","network":"Lusaka City Council","operator":"Lusaka City Council","public_transport:version":"2"},"6022752":{"to":"Chazanga","ref":"71","from":"Town (Kulima Tower)","name":"71 Town (Kulima Tower) - Chazanga","type":"route","route":"bus","network":"Lusaka City Council","operator":"Lusaka City Council","public_transport:version":"2"},"6022892":{"to":"Hospital(UTH)","ref":"17","from":"Town (Kulima Tower)","name":"17 Town (Kulima Tower) - Hospital(UTH)","type":"route","route":"bus","network":"Lusaka City Council","operator":"Lusaka City Council","public_transport:version":"2"},"6022894":{"to":"Town (Kulima Tower)","ref":"17","from":"Hospital (UTH)","name":"17 Hospital (UTH) - Town (Kulima Tower)","type":"route","route":"bus","network":"Lusaka City Council","operator":"Lusaka City Council","public_transport:version":"2"},"6023030":{"to":"Town (Kulima Tower)","ref":"71","from":"Chazanga","name":"71 Chazanga - Town (Kulima Tower)","type":"route","route":"bus","network":"Lusaka City Council","operator":"Lusaka City Council","public_transport:version":"2"},"6023032":{"to":"Town (Kulima Tower)","ref":"59","from":"Woodlands","name":"59 Woodlands - Town (Kulima Tower)","type":"route","route":"bus","network":"Lusaka City Council","public_transport:version":"2"},"6024934":{"to":"Daina Kaima","ref":"33","from":"Town (Kulima Tower)","name":"33 Town (Kulima Tower) - Daina Kaima","type":"route","route":"bus","network":"Lusaka City Council","operator":"Lusaka City Council","public_transport:version":"2"},"6025186":{"to":"Town (Kulima Tower)","ref":"33","from":"Daina Kaima","name":"33 Daina Kaima - Town (Kulima Tower)","type":"route","route":"bus","network":"Lusaka City Council","operator":"Lusaka City Council","public_transport:version":"2"},"6032949":{"to":"Town (Kulima Tower)","ref":"49","from":"Makeni Konga","name":"49 Makeni Konga - Town (Kulima Tower)","type":"route","route":"bus","network":"Lusaka City Council","operator":"Lusaka City Council","public_transport:version":"2"},"6033082":{"to":"Mutendere","ref":"77","from":"Hospital_SDA","name":"77 Hospital_SDA - Mutendere","type":"route","route":"bus","network":"Lusaka City Council","operator":"Lusaka City Council","public_transport:version":"2"},"6034051":{"to":"Kaunda Square","ref":"10","from":"University of Zambia","name":"10 University of Zambia - Kaunda Square","type":"route","route":"bus","network":"Lusaka City Council","operator":"Lusaka City Council","public_transport:version":"2"},"6034052":{"to":"University of Zambia","ref":"10","from":"Kaunda Square","name":"10 Kaunda Square - University of Zambia","type":"route","route":"bus","network":"Lusaka City Council","operator":"Lusaka City Council","public_transport:version":"2"},"6035263":{"to":"Roma","ref":"47","from":"Town (Kulima Tower)","name":"47 Town(Kulima Tower) - Roma","type":"route","route":"bus","network":"Lusaka City Council","operator":"Lusaka City Council","public_transport:version":"2"},"6035303":{"to":"Town (Kulima Tower)","ref":"47","from":"Roma","name":"47 Roma - Town (Kulima Tower)","type":"route","route":"bus","network":"Lusaka City Council","operator":"Lusaka City Council","public_transport:version":"2"},"6035330":{"to":"Ngombe","ref":"45","from":"Town (Kulima Tower)","name":"45 Town (Kulima Tower) - Ngombe","type":"route","route":"bus","network":"Lusaka City Council","operator":"Lusaka City Council","public_transport:version":"2"},"6035339":{"to":"Town (Kulima Tower)","ref":"45","from":"Ngombe","name":"45 Ngombe - Town (Kulima Tower)","type":"route","route":"bus","network":"Lusaka City Council","operator":"Lusaka City Council","public_transport:version":"2"},"6035355":{"to":"New Kasisi","ref":"90","from":"Ngombe","name":"90 Ngombe - New Kasisi","type":"route","route":"bus","network":"Lusaka City Council","operator":"Lusaka City Council","public_transport:version":"2"},"6035370":{"to":"Ngombe","ref":"90","from":"New Kasisi","name":"90 New Kasisi - Ngombe","type":"route","route":"bus","network":"Lusaka City Council","operator":"Lusaka City Council","public_transport:version":"2"},"6037032":{"to":"Airport","ref":"82","from":"Chelston","name":"82 Chelston - Airport","type":"route","route":"bus","network":"Lusaka City Council","operator":"Lusaka City Council","public_transport:version":"2"},"6037044":{"to":"Chelston","ref":"82","from":"Airport","name":"82 Airport - Chelston","type":"route","route":"bus","network":"Lusaka City Council","operator":"Lusaka City Council","public_transport:version":"2"},"6037494":{"to":"Chilenje","ref":"84","from":"Mutendere","name":"84 Mutendere - Chilenje","type":"route","route":"bus","network":"Lusaka City Council","operator":"Lusaka City Council","public_transport:version":"1"},"6037507":{"to":"Mutendere","ref":"84","from":"Chilenje","name":"84 Chilenje - Mutendere","type":"route","route":"bus","network":"Lusaka City Council","operator":"Lusaka City Council","public_transport:version":"1"},"6037533":{"to":"Zanimoune","ref":"87","from":"Town (Millenium)","name":"87 Town (Millenium) - Zanimoune","type":"route","route":"bus","network":"Lusaka City Council","operator":"Lusaka City Council","public_transport:version":"2"},"6037902":{"to":"Town(Millenium)","ref":"87","from":"Zanimoune","name":"87 Zanimoune - Town(Millenium)","type":"route","route":"bus","network":"Lusaka City Council","operator":"Lusaka City Council","public_transport:version":"2"},"6038050":{"to":"Chawama","ref":"42","from":"Town (Kulima Tower)","name":"42 Town (Kulima Tower) - Chawama","type":"route","route":"bus","network":"Lusaka City Council","operator":"Lusaka City Council","public_transport:version":"2"},"6038278":{"to":"Town (Kulima Tower)","ref":"70","from":"Lilayi","name":"70 Lilayi - Town (Kulima Tower)","type":"route","route":"bus","network":"Lusaka City Council","operator":"Lusaka City Council","public_transport:version":"2"},"6038280":{"to":"Lilayi","ref":"70","from":"Town (Kulima Tower)","name":"70 Town (Kulima Tower) - Lilayi","type":"route","route":"bus","network":"Lusaka City Council","operator":"Lusaka City Council","public_transport:version":"2"},"6038436":{"to":"Mbasela","ref":"76","from":"Town (Lumumba)","name":"76 Town (Lumumba) - Mbasela","type":"route","route":"bus","network":"Lusaka City Council","operator":"Lusaka City Council","public_transport:version":"2"},"6038440":{"to":"Town (Lumumba)","ref":"76","from":"Mbasela","name":"76 Mbasela - Town (Lumumba)","type":"route","route":"bus","network":"Lusaka City Council","operator":"Lusaka City Council","public_transport:version":"2"},"6038709":{"to":"Lilanda","ref":"21","from":"Town (City Market)","name":"21 Town (City Market) - Lilanda","type":"route","route":"bus","network":"Lusaka City Council","operator":"Lusaka City Council","public_transport:version":"2"},"6038711":{"to":"Town (City Market)","ref":"21","from":"Lilanda","name":"21 Lilanda - Town (City Market)","type":"route","route":"bus","network":"Lusaka City Council","operator":"Lusaka City Council","public_transport:version":"2"},"6038825":{"to":"Town (Kulima Tower)","ref":"91","from":"Chingwere","name":"91 Chingwere - Town (Kulima Tower)","type":"route","route":"bus","network":"Lusaka City Council","operator":"Lusaka City Council","public_transport:version":"2"},"6038872":{"to":"Makeni Kankole","ref":"75","from":"Town (Kulima Tower)","name":"75 Town (Kulima Tower) - Makeni Kankole","type":"route","route":"bus","network":"Lusaka City Council","operator":"Lusaka City Council","public_transport:version":"2"},"6038873":{"to":"Town (Kulima Tower)","ref":"75","from":"Makeni Kankole","name":"75 Makeni Kankole - Town (Kulima Tower)","type":"route","route":"bus","network":"Lusaka City Council","operator":"Lusaka City Council","public_transport:version":"2"},"6039002":{"to":"Shalom","ref":"95","from":"Town (Lumumba)","name":"95 Town (Lumumba) - Shalom","type":"route","route":"bus","network":"Lusaka City Council","operator":"Lusaka City Council","public_transport:version":"2"},"6039003":{"to":"Town (Lumumba)","ref":"95","from":"Shalom","name":"95 Shalom- Town (Lumumba)","type":"route","route":"bus","network":"Lusaka City Council","operator":"Lusaka City Council","public_transport:version":"2"},"6039063":{"ref":"38","name":"38 Kabanana - Town (Kulima Tower)","type":"route","route":"bus","network":"Lusaka City Council","operator":"Lusaka City Council","public_transport:version":"2"},"6039167":{"to":"Meanwood Chamba Valley","ref":"96","from":"Kaunda Square","name":"96 Kaunda Square - Meanwood Chamba Valley","type":"route","route":"bus","network":"Lusaka City Council","operator":"Lusaka City Council","public_transport:version":"2"},"6039168":{"to":"Kaunda Square","ref":"96","from":"Meanwood Chamba Valley","name":"96 Meanwood Chamba Valley - Kaunda Square","type":"route","route":"bus","network":"Lusaka City Council","operator":"Lusaka City Council","public_transport:version":"2"},"6040093":{"to":"Town (Kulima Tower)","ref":"51","from":"Garden Chilulu","name":"51 Garden Chilulu - Town (Kulima Tower)","type":"route","route":"bus","network":"Lusaka City Council","operator":"Lusaka City Council","public_transport:version":"2"},"6040097":{"to":"Town (Kulima Tower)","ref":"67","from":"Kabulonga/Lake Road","name":"67 Kabulonga/Lake Road - Town (Kulima Tower)","type":"route","route":"bus","network":"Lusaka City Council","operator":"Lusaka City Council","public_transport:version":"2"},"6040212":{"to":"Ngwerere","ref":"94","from":"Town (Millenium)","name":"94 Town (Millenium) - Ngwerere","type":"route","route":"bus","network":"Lusaka City Council","operator":"Lusaka City Council","public_transport:version":"2"},"6040236":{"to":"Town (Millenium)","ref":"94","from":"Ngwerere","name":"94 Ngwerere - Town (Millenium)","type":"route","route":"bus","network":"Lusaka City Council","operator":"Lusaka City Council","public_transport:version":"2"},"6040327":{"to":"Town(Kulima Tower)","ref":"80","from":"Bauleni","name":"80 Bauleni - Town(Kulima Tower)","type":"route","route":"bus","to:en":"Town(Kulima Tower)","from:en":"Bauleni","network":"Lusaka City Council","operator":"Lusaka City Council","public_transport:version":"2"},"6040330":{"to":"Garden house","ref":"79","from":"Town (City market)","name":"79 Town (City market) - Garden house","type":"route","route":"bus","network":"Lusaka City Council","operator":"Lusaka City Council","public_transport:version":"2"},"6040694":{"to":"Town (City market)","ref":"79","from":"Garden house","name":"79 Garden house - Town (Kulima Tower)","type":"route","route":"bus","network":"Lusaka City Council","operator":"Lusaka City Council","public_transport:version":"2"},"6040801":{"to":"Chelston","ref":"97","from":"Avondale","name":"97 Avondale - Chelston","type":"route","route":"bus","network":"Lusaka City Council","operator":"Lusaka City Council","public_transport:version":"2"},"6040803":{"to":"Avondale","ref":"97","from":"Chelston","name":"92 Chelston - Avondale","type":"route","route":"bus","network":"Lusaka City Council","operator":"Lusaka City Council","public_transport:version":"2"},"6040875":{"to":"Ngombe/Roma","ref":"85","from":"Arcades","name":"85 Arcades - Ngombe/Roma","type":"route","route":"bus","to:en":"Ngombe/Roma","from:en":"Arcades","network":"Lusaka City Council","operator":"Lusaka City Council","public_transport:version":"2"},"6041641":{"to":"Longacres","ref":"3","from":"Town (Kulima Tower)","name":"3 Town(Kulima Tower) - Longacres","type":"route","route":"bus","network":"Lusaka City Council","operator":"Lusaka City Council","public_transport:version":"2"},"6041659":{"to":"Town(Kulima Tower)","ref":"3","from":"Longacres","name":"3 Longacres - Town (Kulima Tower)","type":"route","route":"bus","network":"Lusaka City Council","operator":"Lusaka City Council","public_transport:version":"2"},"6041683":{"to":"Chilenje Market","ref":"13","from":"Town (Kulima Tower)","name":"13 Town (Kulima Tower) - Chilenje Market","type":"route","route":"bus","network":"Lusaka City Council","operator":"Lusaka City Council","public_transport:version":"2"},"6041706":{"to":"Town (Kulima Tower)","ref":"13","from":"Chilenje Market","name":"13 Chilenje Market - Town (Kulima Tower)","type":"route","route":"bus","network":"Lusaka City Council","operator":"Lusaka City Council","public_transport:version":"2"},"6041910":{"to":"Kasupe","ref":"58","from":"Town (Lumumba)","name":"58 Town (Lumumba) - Kasupe","type":"route","route":"bus","network":"Lusaka City Council","operator":"Lusaka City Council","public_transport:version":"2"},"6041972":{"to":"Town (Lumumba)","ref":"58","from":"Kasupe","name":"58 Kasupe - Town (Lumumba)","type":"route","route":"bus","network":"Lusaka City Council","operator":"Lusaka City Council","public_transport:version":"2"},"6041994":{"to":"Makeni Simoson","ref":"73","from":"Town (City Market)","name":"73 Town (City Market) - Makeni Simoson","type":"route","route":"bus","network":"Lusaka City Council","operator":"Lusaka City Council","public_transport:version":"2"},"6041999":{"to":"Town (City Market)","ref":"73","from":"Makeni Simoson","name":"73 Makeni Simoson - Town (City Market)","type":"route","route":"bus","network":"Lusaka City Council","operator":"Lusaka City Council","public_transport:version":"2"},"6042026":{"to":"Farmers","ref":"72","from":"Town (City Market)","name":"72 Town (City Market) - Farmers","type":"route","route":"bus","network":"Lusaka City Council","operator":"Lusaka City Council","public_transport:version":"2"},"6042038":{"to":"Town (City Market)","ref":"72","from":"Farmers","name":"72 Farmers - Town (City Market)","type":"route","route":"bus","network":"Lusaka City Council","operator":"Lusaka City Council","public_transport:version":"2"},"6042056":{"to":"Kanyama","ref":"74","name":"74 Town (City Market) - Kanyama","type":"route","route":"bus","network":"Lusaka City Council","operator":"Lusaka City Council","public_transport:version":"2"},"6042065":{"to":"Town (City Market)","ref":"74","from":"Kanyama","name":"74 Kanyama - Town (City Market)","type":"route","route":"bus","network":"Lusaka City Council","operator":"Lusaka City Council","public_transport:version":"2"},"6042181":{"to":"Maplot","ref":"34","from":"Town (City Market)","name":"34 Town (City Market) - Maplot","type":"route","route":"bus","network":"Lusaka City Council","operator":"Lusaka City Council","public_transport:version":"2"},"6042267":{"to":"Town(City Market)","ref":"34","from":"Maplot","name":"34 Maplot - Town (City Market)","type":"route","route":"bus","network":"Lusaka City Council","operator":"Lusaka City Council","public_transport:version":"2"},"6043220":{"to":"Matero","ref":"24","from":"Town (City market)","name":"24 Town (City Market) - Matero","type":"route","route":"bus","network":"Lusaka City Council","operator":"Lusaka City Council","public_transport:version":"2"},"6043288":{"to":"Zingalume","ref":"69","from":"Town (City market)","name":"69 Town (City market) - Zingalume","type":"route","route":"bus","network":"Lusaka City Council","operator":"Lusaka City Council","public_transport:version":"2"},"6047181":{"to":"Town (City Market)","ref":"24","from":"Matero","name":"24 Matero - Town (City Market)","type":"route","route":"bus","network":"Lusaka City Council","operator":"Lusaka City Council","public_transport:version":"2"},"6049732":{"to":"Mulanga","ref":"60","from":"Town (Lumumba)","name":"60 Town (Lumumba) - Mulanga","type":"route","route":"bus","network":"Lusaka City Council","operator":"Lusaka City Council","public_transport:version":"2"},"6049873":{"to":"Town (Lumumba)","ref":"60","from":"Mulanga","name":"60 Mulanga - Town (Lumumba)","type":"route","route":"bus","network":"Lusaka City Council","operator":"Lusaka City Council","public_transport:version":"2"},"6049971":{"to":"Kamanga","ref":"61","from":"Town (Lumumba)","name":"61 Town (Lumumba) - Kamanga","type":"route","route":"bus","network":"Lusaka City Council","operator":"Lusaka City Council","public_transport:version":"2"},"6061750":{"to":"Town (City market)","ref":"69","from":"Zingalume","name":"69 Zingalume - Town (City market)","type":"route","route":"bus","network":"Lusaka City Council","operator":"Lusaka City Council","public_transport:version":"2"},"6061905":{"to":"Town (Lumumba)","ref":"61","from":"Kamanga","name":"61 Kamanga - Town (Lumumba)","type":"route","route":"bus","network":"Lusaka City Council","operator":"Lusaka City Council","public_transport:version":"2"},"6062416":{"to":"John Howard","ref":"46","from":"Town (Kulima Tower)","name":"46 Town (Kulima Tower) - John Howard","type":"route","route":"bus","network":"Lusaka City Council","operator":"Lusaka City Council","public_transport:version":"2"},"6062514":{"to":"Longacres","ref":"88","from":"Kabulonga/Lake Road","name":"88 Kabulonga/Lake Road - Longacres","type":"route","route":"bus","network":"Lusaka City Council","operator":"Lusaka City Council","public_transport:version":"2"},"6067955":{"to":"Town (City Market)","ref":"27","from":"Kalikiliki","name":"27 Kalikiliki - Town (City Market)","type":"route","route":"bus","network":"Lusaka City Council","operator":"Lusaka City Council","public_transport:version":"2"},"6070372":{"to":"Town (Millenium)","ref":"8","from":"Kaunda Square","name":"8 Kaunda Square - Town (Millenium)","type":"route","route":"bus","network":"Lusaka City Council","operator":"Lusaka City Council","public_transport:version":"2"},"6070451":{"to":"Mandevu","ref":"37","from":"Town (City Market)","name":"37 Town (City Market) - Mandevu","type":"route","route":"bus","network":"Lusaka City Council","operator":"Lusaka City Council","public_transport:version":"2"},"6070471":{"to":"Town (City Market)","ref":"37","from":"Mandevu","name":"37 Mandevu - Town (City Market)","type":"route","route":"bus","network":"Lusaka City Council","operator":"Lusaka City Council","public_transport:version":"2"},"10390883":{"to":"Pancerniaków","ref":"( 159 )","from":"Os. Poręba","name":"( 159 ) : os. Poręba - Pancerniaków","type":"route","route":"bus","colour":"blue","network":"Lublin","operator":"ZTM Lublin"},"10390886":{"to":"Pancerniaków","ref":"( 150 )","from":"Węglin","name":"( 150 ) : Węglin - Pancerniaków","type":"route","route":"bus","colour":"blue","network":"Lublin","operator":"ZTM Lublin"},"10391067":{"to":"Metalurgiczna","ref":"( 45 )","from":"Gęsia","name":"( 45 ) : Gęsia - Metalurgiczna","type":"route","route":"bus","colour":"blue","network":"Lublin","operator":"ZTM Lublin"},"15768560":{"to":"Macclesfield","ref":"19A","from":"Whirley Barn","name":"D&G Route 19A: Whirley Barn to Macclesfield","type":"route","route":"bus","operator":"D&G Bus","opening_hours":"Mo-Sa","public_transport:version":"2"}}