{"13169242":{"to":"Andoharanofotsy","ref":"N 60","from":"Ambohimangakely","name":"Route nationale 60","type":"route","route":"road","network":"MG:RN-road","alt_name":"Boulevard de Tokyo","wikidata":"Q15992001","wikipedia":"fr:Route nationale 60 (Madagascar)"},"15536317":{"to":"Toliara","ref":"N 7","from":"Antananarivo","name":"Route nationale 7","type":"route","route":"road","network":"MG:RN-road","wikidata":"Q3941905"},"16067865":{"ref":"N 4","name":"Route nationale 4","type":"route","route":"road","network":"MG:RN-road","wikidata":"Q3941901"},"16068014":{"to":"Toamasina","ref":"N 2","from":"Antananarivo","name":"Route nationale 2","type":"route","route":"road","network":"MG:RN-road","wikidata":"Q3941904"},"16068015":{"to":"Antsiranana","ref":"N 6","from":"Ambondromamy","name":"Route nationale 6","type":"route","route":"road","network":"MG:RN-road","wikidata":"Q14475271","description":"Ambondromamy – Antsohihy – Ambanja – Ambilobe - Antsiranana"},"16068353":{"ref":"N 3","from":"Antananarivo","name":"Route nationale 3","type":"route","route":"road","network":"MG:RN-road","wikidata":"Q3941903"},"16069008":{"to":"Toamasina","ref":"N 2b","from":"Antananarivo","name":"Route nationale 2b","type":"route","route":"road","network":"MG:RN-road","wikidata":"Q65244554"},"16069031":{"ref":"N 65","name":"Route nationale 65","type":"route","route":"road","network":"MG:RN-road","wikidata":"Q116007923","wikipedia":"fr:Route nationale 65 (Madagascar)"},"16069059":{"ref":"N 8a","name":"Route nationale 8a","type":"route","route":"road","network":"MG:RN-road","wikidata":"Q15302755"},"16069060":{"to":"Bekopaka","ref":"N 8","from":"Morondava","name":"Route nationale 8","type":"route","route":"road","network":"MG:RN-road","distance":"198","wikidata":"Q17320698"},"16069131":{"to":"Maintirano","ref":"N 19","from":"Katsepy","name":"Route nationale 19","type":"route","route":"road","network":"MG:RN-road","wikidata":"Q22809381","wikipedia":"fr:Route nationale 19 (Madagascar)"},"16069132":{"to":"Maintirano","ref":"N 1b","from":"Analavory","name":"Route nationale 1b","type":"route","route":"road","network":"MG:RN-road","wikidata":"Q16597394"},"16069184":{"to":"Sambaina","ref":"N 43","from":"Analavory","name":"Route nationale 43","type":"route","route":"road","network":"MG:RN-road","wikidata":"Q22812332","wikipedia":"fr:Route nationale 43 (Madagascar)"},"16069185":{"to":"Tsiroanomandidy","ref":"N 1","from":"Antananarivo","name":"Route nationale 1","type":"route","route":"road","network":"MG:RN-road","wikidata":"Q15097958"},"16074563":{"to":"Ankify","ref":"N 30","from":"Madirofolo","name":"Route nationale 30","type":"route","route":"road","network":"MG:RN-road","distance":"17","wikidata":"Q22811680","description":"Madirofolo – Ankify"},"16074657":{"to":"Marofinaritra","ref":"N 5a","from":"Ambilobe","name":"Route nationale 5a","type":"route","route":"road","network":"MG:RN-road","distance":"414","wikidata":"Q14475270","description":"Ambilobe – Sambava – Antalaha – Marofinaritra"},"16078441":{"ref":"N 58a","name":"Route nationale 58a","type":"route","route":"road","network":"MG:RN-road","wikidata":"Q22812401","wikipedia":"fr:Route nationale 58a (Madagascar)"},"16078681":{"to":"Toliara","ref":"N 35","from":"Antananarivo","name":"Route nationale 35","type":"route","route":"road","wikidata":"Q15097933"},"16085881":{"ref":"N 12a","name":"Route nationale 12a","type":"route","route":"road","network":"MG:RN-road","wikidata":"Q16293014"},"16085882":{"ref":"N 13","name":"Route nationale 13","type":"route","route":"road","network":"MG:RN-road","wikidata":"Q15097926"},"16086015":{"ref":"N 33a","name":"Route nationale 33a","type":"route","route":"road","network":"MG:RN-road","wikidata":"Q22812174"},"16086588":{"ref":"N 8c","name":"Route nationale 8c","type":"route","route":"road","network":"MG:RN-road","wikidata":"Q22809359"},"16086630":{"ref":"N 44","name":"Route nationale 44","type":"route","route":"road","network":"MG:RN-road","wikidata":"Q22812359"},"16086631":{"ref":"N 3a","name":"Route nationale 3a","type":"route","route":"road","network":"MG:RN-road","wikidata":"Q16597406"},"16086642":{"ref":"N 5","name":"Route nationale 5","type":"route","route":"road","network":"MG:RN-road","wikidata":"Q15097950"},"16086643":{"ref":"N 22","name":"Route nationale 22","type":"route","route":"road","network":"MG:RN-road","wikidata":"Q18088362"},"16087525":{"ref":"N 30a","name":"Route nationale 30a","type":"route","route":"road","network":"MG:RN-road","distance":"28","wikidata":"Q22812100"},"16087526":{"ref":"N 57","name":"Route nationale 57","type":"route","route":"road","network":"MG:RN-road","wikidata":"Q22812399"},"16087541":{"ref":"N 31","name":"Route nationale 31","type":"route","route":"road","network":"MG:RN-road","wikidata":"Q17493011"},"16087542":{"ref":"N 31a","name":"Route nationale 31a","type":"route","route":"road","network":"MG:RN-road","wikidata":"Q22812122"},"16087543":{"ref":"N 32","name":"Route nationale 32","type":"route","route":"road","network":"MG:RN-road","wikidata":"Q17492997"},"16115819":{"ref":"N 10","name":"Route nationale 10","type":"route","route":"road","network":"MG:RN-road","wikidata":"Q15302745"},"16115820":{"ref":"N 17a","name":"Route nationale 17a","type":"route","route":"road","network":"MG:RN-road","wikidata":"Q22809375"},"16117824":{"ref":"N 54","name":"Route nationale 54","type":"route","route":"road","network":"MG:RN-road","wikidata":"Q22812391"},"16117868":{"ref":"N 52","name":"Route nationale 52","type":"route","route":"road","network":"MG:RN-road","wikidata":"Q16293024"},"16119819":{"ref":"N 12","name":"Route nationale 12","type":"route","route":"road","network":"MG:RN-road","wikidata":"Q18088390"}}